OpenSecrets_Senators_Industries/__init__.py
OpenSecrets_Senators_Industries/OpenSecrets_Senators_Industries.py
opensecrets_senators_industries-0.1.0.dist-info/LICENSE
opensecrets_senators_industries-0.1.0.dist-info/WHEEL
opensecrets_senators_industries-0.1.0.dist-info/METADATA
opensecrets_senators_industries-0.1.0.dist-info/RECORD
