Metadata-Version: 2.1
Name: opensecrets-senators-industries
Version: 0.1.0
Summary: Python package using the OpenSecrets and ProPublica APIs to allow users to view information about their senators and the industries that fund them
License: MIT
Author: Jade Qiu
Requires-Python: >=3.9,<4.0
Classifier: License :: OSI Approved :: MIT License
Classifier: Programming Language :: Python :: 3
Classifier: Programming Language :: Python :: 3.10
Classifier: Programming Language :: Python :: 3.9
Requires-Dist: bs4 (>=0.0.1,<0.0.2)
Requires-Dist: lxml (>=4.7.1,<5.0.0)
Requires-Dist: pandas (>=1.3.5,<2.0.0)
Requires-Dist: python-dotenv (>=0.19.2,<0.20.0)
Requires-Dist: requests (>=2.26.0,<3.0.0)
Requires-Dist: unittest (>=0.0,<0.1)
